yelp_bytes/__init__.py
yelp_bytes/py.typed
yelp_bytes-0.4.4.dist-info/METADATA
yelp_bytes-0.4.4.dist-info/WHEEL
yelp_bytes-0.4.4.dist-info/top_level.txt
yelp_bytes-0.4.4.dist-info/RECORD
