Metadata-Version: 2.1
Name: yelp-bytes
Version: 0.4.4
Summary: Utilities for dealing with byte strings, invented and maintained by Yelp.
Home-page: https://github.com/Yelp/yelp_bytes
Author: Buck Evan
Author-email: buck@yelp.com
License: UNKNOWN
Platform: all
Classifier: Programming Language :: Python :: 3
Classifier: Programming Language :: Python :: 3.6
Classifier: Programming Language :: Python :: 3.7
Classifier: Programming Language :: Python :: 3.8
Classifier: Programming Language :: Python :: Implementation :: PyPy
Classifier: License :: OSI Approved :: The Unlicense (Unlicense)
Requires-Python: >=3.6
Requires-Dist: yelp-encodings
